{
  "template_id": "template_town_guard",
  "name": {
    "en": "Town Guard",
    "ko": "경비병"
  },
  "description": {
    "en": "A vigilant guard patrolling the area between the town square and the harbor.",
    "ko": "광장과 항구 사이를 순찰하는 경계심 많은 경비병입니다."
  },
  "monster_type": "NEUTRAL",
  "behavior": "ROAMING",
  "faction_id": "ash_knights",
  "stats": {
    "strength": 14,
    "dexterity": 12,
    "constitution": 14,
    "intelligence": 10,
    "wisdom": 12,
    "charisma": 10,
    "level": 8
  },
  "experience_reward": 0,
  "gold_reward": 0,
  "drop_items": [],
  "respawn_time": 0,
  "aggro_range": 0,
  "roaming_range": 3,
  "spawn_config": {
    "count": 1,
    "global_max_count": 1,
    "area_filter": {
      "x_range": [0, 0],
      "y_range": [0, 9]
    },
    "distribution": "random",
    "roaming": {
      "enabled": true,
      "roam_chance": 0.3,
      "roaming_area": {
        "min_x": 0,
        "max_x": 0,
        "min_y": 0,
        "max_y": 9
      }
    }
  },
  "properties": {
    "dialogue": {
      "en": [
        "Stay alert, citizen. These streets aren't always safe.",
        "I'm on patrol. Keep moving.",
        "Report any suspicious activity to me immediately."
      ],
      "ko": [
        "경계를 늦추지 마시오, 시민. 이 거리가 항상 안전한 것은 아니니까.",
        "순찰 중이오. 계속 가시오.",
        "수상한 활동이 있으면 즉시 나에게 보고하시오."
      ]
    },
    "greeting": {
      "en": "The guard eyes you suspiciously.",
      "ko": "경비병이 당신을 의심스럽게 쳐다봅니다."
    }
  }
}
